pyqbpp.py
pyqbpp-2025.5.11.dist-info/licenses/LICENSE
pyqbpp-2025.5.11.dist-info/METADATA
pyqbpp-2025.5.11.dist-info/WHEEL
pyqbpp-2025.5.11.dist-info/top_level.txt
pyqbpp-2025.5.11.dist-info/RECORD
